setup.cfg
setup.py
dropSeqPipe/__init__.py
dropSeqPipe/__main__.py
dropSeqPipe.egg-info/PKG-INFO
dropSeqPipe.egg-info/SOURCES.txt
dropSeqPipe.egg-info/dependency_links.txt
dropSeqPipe.egg-info/entry_points.txt
dropSeqPipe.egg-info/not-zip-safe
dropSeqPipe.egg-info/requires.txt
dropSeqPipe.egg-info/top_level.txt
dropSeqPipe/Python/merge_results.py
dropSeqPipe/Rscripts/STAR_log_plot.R
dropSeqPipe/Rscripts/fastqc.R
dropSeqPipe/Snakefiles/bulk/fastqc.snake
dropSeqPipe/Snakefiles/bulk/post_align.snake
dropSeqPipe/Snakefiles/bulk/pre_align.snake
dropSeqPipe/Snakefiles/bulk/star_align.snake
dropSeqPipe/Snakefiles/singleCell/Dropseq_post_kallisto_align.temp.snake
dropSeqPipe/Snakefiles/singleCell/extract_expression.snake
dropSeqPipe/Snakefiles/singleCell/extract_expression_single.snake
dropSeqPipe/Snakefiles/singleCell/extract_species.snake
dropSeqPipe/Snakefiles/singleCell/fastqc.snake
dropSeqPipe/Snakefiles/singleCell/other_star_align.temp.snake
dropSeqPipe/Snakefiles/singleCell/post_align.snake
dropSeqPipe/Snakefiles/singleCell/pre_align.snake
dropSeqPipe/Snakefiles/singleCell/sircel_align.temp.snake
dropSeqPipe/Snakefiles/singleCell/star_align.snake
dropSeqPipe/Snakefiles/singleCell/test.temp.snake